django_peeringdb/__init__.py
django_peeringdb/const.py
django_peeringdb/default_settings.py
django_peeringdb/fields.py
django_peeringdb/admin/__init__.py
django_peeringdb/admin/views.py
django_peeringdb/client_adaptor/__init__.py
django_peeringdb/client_adaptor/backend.py
django_peeringdb/client_adaptor/load.py
django_peeringdb/client_adaptor/setup.py
django_peeringdb/management/__init__.py
django_peeringdb/management/commands/__init__.py
django_peeringdb/management/commands/pdb_sync.py
django_peeringdb/migrations/0001_initial.py
django_peeringdb/migrations/0002_network_fields_help_text.py
django_peeringdb/migrations/0003_never_via_route_servers.py
django_peeringdb/migrations/0004_rs_lg_fields.py
django_peeringdb/migrations/0005_fac_contacts.py
django_peeringdb/migrations/0006_net_operational.py
django_peeringdb/migrations/0007_add_verbose_names.py
django_peeringdb/migrations/0008_traffic_levels.py
django_peeringdb/migrations/0009_ixlanprefix_in_dfz.py
django_peeringdb/migrations/0010_ix_ixf_fields.py
django_peeringdb/migrations/0011_ixlan_ixf_fields.py
django_peeringdb/migrations/0012_change_network_prefixes_and_info_type.py
django_peeringdb/migrations/0013_add_phone_help_text.py
django_peeringdb/migrations/0014_add_suite_and_floor.py
django_peeringdb/migrations/0015_add_aka_longname.py
django_peeringdb/migrations/0016_add_ix_service_and_terms.py
django_peeringdb/migrations/0017_facility_fields.py
django_peeringdb/migrations/0018_add_region_continent_field.py
django_peeringdb/migrations/0019_ix_add_sales_phone_email.py
django_peeringdb/migrations/0020_status_dashboard.py
django_peeringdb/migrations/0021_rir_fields.py
django_peeringdb/migrations/0022_carriers.py
django_peeringdb/migrations/0023_mtu.py
django_peeringdb/migrations/0024_carrier_website_optional.py
django_peeringdb/migrations/0025_campus.py
django_peeringdb/migrations/0026_add_social_media.py
django_peeringdb/migrations/0027_auto_20230804_1414.py
django_peeringdb/migrations/0028_auto_20240109_1157.py
django_peeringdb-3.7.0.dist-info/METADATA
django_peeringdb-3.7.0.dist-info/WHEEL
django_peeringdb-3.7.0.dist-info/licenses/LICENSE.txt
django_peeringdb-3.7.0.dist-info/RECORD
