Metadata-Version: 2.4
Name: django-peeringdb
Version: 3.7.0
Summary: PeeringDB Django models
Project-URL: repository, https://github.com/peeringdb/django-peeringdb
Author-email: PeeringDB <support@peeringdb.com>
License: BSD-2-Clause
License-File: LICENSE.txt
Classifier: Development Status :: 5 - Production/Stable
Classifier: Framework :: Django :: 3.1
Classifier: Framework :: Django :: 3.2
Classifier: Framework :: Django :: 4.0
Classifier: Intended Audience :: Developers
Classifier: License :: OSI Approved :: Apache Software License
Classifier: Programming Language :: Python :: 3.10
Classifier: Programming Language :: Python :: 3.11
Classifier: Programming Language :: Python :: 3.12
Classifier: Programming Language :: Python :: 3.13
Classifier: Programming Language :: Python :: 3.14
Classifier: Topic :: Internet
Classifier: Topic :: Software Development :: Libraries :: Python Modules
Requires-Python: >=3.10
Requires-Dist: asgiref>=3
Requires-Dist: django-countries>1
Requires-Dist: django-handleref>=2
Requires-Dist: django-inet>=1
Requires-Dist: django>=4.2
